{
    "greetings": {
    "hai": "Hi",
    "hello": "Hello",
    "namaskaram": "Hello (formal)",
    "ela unnav": "How are you? (casual)",
    "ela unnaru": "How are you? (respectful)",
    "bagunnava": "Are you fine? (casual)",
    "bagunnara": "Are you fine? (respectful)",
    "suprabhatam": "Good morning",
    "shubha sayamtram": "Good evening",
    "shubha ratri": "Good night",
    "veedkolu": "Goodbye"
  },
  "romanatic": {
    "i am crazy about you": "ninnu chusi pichi ekkuthundi",
    "you are my everything": "nuvvu naaku prapancham antha",
    "i will always be with you": "nenu nee tho eppudu undipotha",
    "you stole my heart": "nuvvu na hrudayam donga chesav",
    "hold my hand forever": "na cheyi eppudu vadalakunda pattuko",
    "your smile melts me": "nee navvu nannu karipestundi",
    "i want to spend my whole life with you": "nee tho na jeevitham motham spend cheyyali",
    "you are my first and last love": "nuvve na modati prema, last prema",
    "without you my day is incomplete": "ninnu choodakunda na roju poorthi kaadu",
    "your one smile is enough": "nee okka navvu chaalu na badhalu anni maripothayi",
    "you are my life": "nuvve na jeevitham",
    "i really like you": "nuvvu naku chala ishtam",
    "i want you in my life": "nuvvu naku kavali",
    "i want to be with you": "naku neetho undalani undi",
    "you look stunning": "nuvvu chala andamga unnav",
    "you are so cute": "nuvvu chala bujji ga unnav",
    "you are my gold": "nuvvu na bangaram",
    "you are my heartbeat": "nuvvu na hrudaya spandana",
    "all my dreams are about you": "naa kalalanni nee chuttu tiruguthunnayi",
    "even waiting for you feels beautiful": "nee kosam edhuru choodadam kuda andamaina anubhavam",
    "your love gave meaning to my life": "nee prema na jeevithaniki ardham ichindi",
    "as long as you are with me, no fear": "nuvvu na jeevitham lo unna roju naa bhayam ki sthanam ledu",
    "i am only yours": "nenu neeke sontham",
    "you make every day special": "nuvvu unte prathi roju special avuthundi",
    "i cant live without you": "nuvvu lekunda brathakalekapothunna",
    "you are the most beautiful person": "nuvvu na chusthunna andamaina vyakthi",
    "kiss me": "nannu muddu pettuko",
    "i adore you": "ninnu chala preminchutunna"
  },
  "mood": {
    "feeling low": "mind lo undi",
    "overjoyed": "chala anandam ga undi",
    "frustrated": "irritation ga undi",
    "peaceful": "shantham ga undi",
    "nervous": "bayam ga undi",
    "energetic": "energy tho undi",
    "sleepy": "nidra vastundi",
    "kopam": "Angry",
    "happy": "Happy",
    "sad": "Sad",
    "boring": "Boring",
    "excited": "Excited",
    "tired": "Tired",
    "confused": "Confused",
    "ayyo": "Oh no / Disappointed",
    "abba": "Wow / Surprise / Relief"
  },
  "slang": {
    "ra": "Come here (to guy, casual)",
    "raa": "Come here (very casual)",
    "poyi": "Go away",
    "machha": "Dude / Bro",
    "bava": "Bro / Friend",
    "annaa": "Elder brother / Bro",
    "akka": "Elder sister",
    "babu": "Baby / Dear",
    "light le": "Chill / No problem",
    "super undi": "It's awesome",
    "em jarigindi": "What happened?",
    "endi bro": "What's up bro?",
    "pakka": "Sure / Confirmed",
    "bindaas": "Carefree / Chill",
    "scene enti": "What's the scene?",
    "light teesuko": "Take it easy",
    "inka": "More",
    "ayyayyo": "Oh no / Exasperation"
  },
  "daily_use": {
    "neeru": "Water",
    "bhojanam": "Food / Meal",
    "emi chestunnav": "What are you doing?",
    "ekkada unnav": "Where are you?",
    "nenu vastunna": "I'm coming",
    "time enti": "What is the time?",
    "thanks": "Thank you",
    "sorry": "Sorry",
    "parledu": "It's okay / No problem",
    "avunu": "Yes",
    "ledu": "No",
    "nenu": "I",
    "nuvvu": "You (casual)",
    "meeru": "You (respectful)",
    "entha": "How much",
    "bagundi": "It's good",
    "tinnava": "Did you eat?"
  },
  "food_drinks": {
    "aakali ga undi": "I'm hungry",
    "neeru ivvandi": "Please give water",
    "menu ivvandi": "Please give the menu",
    "idi enti": "What is this?",
    "karam unda": "Is it spicy?",
    "shakahaari": "Vegetarian",
    "mamsahaari": "Non-vegetarian",
    "bhojanam cheddam": "Let's eat",
    "tiffin": "Breakfast / Snacks",
    "annam": "Rice",
    "chai": "Tea",
    "coffee": "Coffee"
  },
  "shopping": {
    "idi entha": "How much is this?",
    "konchem thaggisthara": "Can you reduce the price?",
    "naku idi kavali": "I want this",
    "edi best": "Which is the best?",
    "bill ivvandi": "Please give the bill",
    "bagundi": "It's good",
    "ledhu": "No / Not needed"
  },
  "travel": {
    "ekkadiki potunnav": "Where are you going?",
    "intiki vellali": "I want to go home",
    "bus ekkada": "Where is the bus?",
    "auto ekkada": "Where is the auto?",
    "station ekkada": "Where is the station?",
    "repu vastunna": "I'm coming tomorrow",
    "safe ga undi": "It's safe"
  },
  "family": {
    "amma": "Mother",
    "nanna": "Father",
    "anna": "Elder brother",
    "akka": "Elder sister",
    "tammudu": "Younger brother",
    "chelli": "Younger sister",
    "bava": "Brother-in-law",
    "vadina": "Sister-in-law",
    "inti vallu": "Family members",
    "pillalu": "Children"
  },
  "work_office": {
    "office ki vellali": "I have to go to office",
    "meeting undi": "There is a meeting",
    "work undi": "There is work",
    "complete chesa": "I completed it",
    "emi plan": "What's the plan?",
    "deadline enti": "What is the deadline?"
  },
  "funny_casual": {
    "em scene ra": "What's the scene bro?",
    "full enjoy": "Full enjoy",
    "pandaga chesko": "Enjoy / Celebrate",
    "jaga": "Waste / Useless",
    "cat": "Flattery / Fake praise",
    "thokka": "Nonsense",
    "abbey": "Hey dude"
  },
  "compliments": {
    "nuvvu chala andamga unnav": "You look very beautiful",
    "nee navvu chala andamga undi": "Your smile is very beautiful",
    "nee pani goppaga undi": "Your work is great",
    "nuvvu chala smart ga unnav": "You look very smart",
    "idi adbhutamaina alochana": "This is a wonderful idea",
    "nuvvu chala talented": "You are very talented",
    "nuvvu today chala bagunnav": "You look great today",
    "nee presentation bagundi": "Your presentation was good",
    "nuvvu chala graceful ga unnav": "You are very graceful"
  },
  "health": {
    "nenu arogyamga unna": "I am healthy",
    "nenu doctor ni chustunna": "I am seeing a doctor",
    "naaku jwaram undi": "I have fever",
    "naaku head ache undi": "I have a headache",
    "mandu ivvandi": "Please give medicine",
    "hospital ekkada": "Where is the hospital?",
    "naaku pain undi": "I have pain",
    "nenu healthy ga undali": "I want to be healthy",
    "exercise cheyyali": "I should exercise",
    "rest teesuko": "Take rest"
  },
  "motivation_success": {
    "nuvvu win avthav": "You will win",
    "try cheyyi": "Try it",
    "never give up": "Never give up",
    "nuvvu chala strong": "You are very strong",
    "success vastundi": "Success will come",
    "hard work cheyyi": "Do hard work",
    "nuvvu capable": "You are capable",
    "goal reach cheyyali": "You have to reach the goal",
    "positive ga undu": "Stay positive"
  },
  "weather": {
    "end undi": "It's sunny / hot",
    "chala chali ga undi": "It's very cold",
    "varsham padtundi": "It's raining",
    "vatawaranam bagundi": "The weather is good",
    "thum midiyundi": "It's foggy",
    "gali vastundi": "Wind is blowing",
    "chala humid undi": "It's very humid"
  },
  "arguing": {
    "endi problem": "What's the problem?",
    "nuvvu enduku ala cheptunnav": "Why are you saying like that?",
    "nenu cheppaledu": "I didn't say that",
    "stop cheyyi": "Stop it",
    "naku time ledu": "I don't have time",
    "em jarigindi": "What happened?",
    "parledu": "It's okay (sarcastic)",
    "nuvvu wrong": "You are wrong",
    "calm ga undu": "Stay calm"
  },
  "numbers": {
    "one": "okati",
    "two": "rendu",
    "three": "moodu",
    "four": "nalugu",
    "five": "aidu",
    "ten": "padi",
    "twenty": "iravai",
    "hundred": "nuru",
    "thousand": "veyyi"
  },
  "directions": {
    "left": "edama",
    "right": "kudi",
    "straight": "straight",
    "near": "daggara",
    "far": "dura",
    "opposite": "eduruga",
    "behind": "venaka",
    "in front": "mundu"
  },
  "school_college": {
    "exam undi": "exam undi",
    "homework cheyyali": "homework cheyyali",
    "class miss ayyindi": "class miss ayyindi",
    "teacher ela unnar": "teacher ela unnar",
    "pass ayyana": "pass ayyana",
    "fail ayyana": "fail ayyana",
    "notes ivvu": "notes ivvu"
    },
  "romantic": {
    "miss": ["ninnu miss ayya", "chala miss avthunna", "inka miss avthunna"],
    "love": ["ninnu chala ishtam", "nuvvu naadi", "love chesthunnanu"]
  },
  "attitude": {
    "why": ["enti ra", "enti idi", "enduku ila chesthunav"],
    "where": ["ekkada vellavu", "ekkada unnav"]
  },
  "clingy": {
    "talk": ["naatho matladu", "inka matladava", "ignore chesthunava"],
    "come": ["ra ikkadiki", "come here ra"]
  },
  "teasing": {
    "idiot": ["pichi vada", "mental ra nuvvu 😏"],
    "naughty": ["chala naughty ga unnav 😏"]
  }
}
